{
    "video_id": "083ed109867927558105c456704d5120",
    "description": "",
    "url": "./data/segments/3F2rz23IKUk-Scene-054.mp4",
    "frame_number": 0,
    "interval_seconds": 1,
    "batch_size": 2,
    "batch_step": 2,
    "caption": "The video features a panel discussion on a stage with three individuals seated in wooden chairs, facing an audience. The setting is well-lit with purple and white spotlights creating a vibrant atmosphere. A man on the left, dressed in a white shirt and dark pants, listens attentively with his hands clasped. In the center, a woman wearing a black t-shirt and black pants sits with her hands resting on her lap, also paying close attention to the conversation. On the right, another man in a gray suit gestures animatedly as he speaks, indicating that he is likely the one leading the discussion at this moment. The stage setup includes a table with a computer motherboard design, suggesting the topic might be related to technology or innovation. The overall mood appears professional yet engaging, with all participants actively involved in the dialogue."
}