{
    "video_id": "20535865ff49fb51de4df25e486843c2",
    "description": "",
    "url": "./data/segments/3iUTkJy84EY-Scene-239.mp4",
    "frame_number": 0,
    "interval_seconds": 1,
    "batch_size": 2,
    "batch_step": 2,
    "caption": "The video features a woman with shoulder-length dark hair and glasses, wearing a light green top with floral embroidery. She is seated against a plain black background, which helps to focus attention on her. The woman appears to be engaged in a conversation or presentation, as she is gesturing with her hands while speaking. Her expressions and hand movements suggest that she is explaining something, possibly in an educational or professional context. The setting seems formal, indicated by her attire and the microphone clipped to her top, suggesting that this could be part of a lecture, interview, or instructional video. The logo in the bottom left corner reads \"NPTEL,\" hinting that the content might be related to an educational program or course."
}