{
    "video_id": "964ae6be6827bdc7147d75f71516d9a8",
    "description": "",
    "url": "./data/segments/3kf1gQNnb-8-Scene-152.mp4",
    "frame_number": 0,
    "interval_seconds": 1,
    "batch_size": 2,
    "batch_step": 2,
    "caption": "The video features a man sitting in what appears to be a recording studio, indicated by the soundproofing panels on the wall behind him. He is wearing large headphones and is positioned in front of a professional microphone, suggesting that he is either hosting a podcast or participating in a radio show. The man has a beard and is dressed casually in a black jacket over a gray shirt. His expression changes slightly between the two frames, indicating that he is engaged in conversation or reacting to something being said. The setting and his attire suggest a relaxed yet professional atmosphere typical of audio recording environments."
}