{
    "video_id": "f27286d0b6758adc3a75ba10c6121337",
    "description": "",
    "url": "./data/segments/3P5zYKAFzh4-Scene-008.mp4",
    "frame_number": 0,
    "interval_seconds": 1,
    "batch_size": 2,
    "batch_step": 2,
    "caption": "The video captures a vibrant and dynamic stage setup, likely for a live performance or event. The stage is illuminated with an array of colorful laser lights in shades of purple, blue, and green, creating a visually striking atmosphere. A large screen in the background displays the word \"SLUSH\" prominently, suggesting the name of the event or venue. On the right side of the screen, there is a smaller inset showing a person, possibly a host or performer, who appears to be speaking or reacting to something happening on stage. The audience is seated in rows, facing the stage, indicating that this is a live event with an engaged crowd. The overall ambiance is energetic and festive, typical of a concert or entertainment show."
}