{
    "video_id": "d47c160c2eb709f955f01b0c74f142fc",
    "description": "",
    "url": "./data/segments/3fPjWUG7DxI-Scene-071.mp4",
    "frame_number": 0,
    "interval_seconds": 1,
    "batch_size": 2,
    "batch_step": 2,
    "caption": "The video features a person with a distinctive, tall, and spiky hairstyle, wearing glasses, a white shirt, gold suspenders, and a red bow tie. They are seated in front of a microphone, suggesting they are either hosting or participating in a podcast. The background is filled with framed photographs and memorabilia, indicating a personal or professional space dedicated to memories or achievements. The individual appears to be engaged in conversation, possibly sharing stories or insights, as they look directly ahead with a focused expression. The setting and attire suggest a casual yet professional atmosphere, likely aimed at an audience interested in personal narratives or discussions."
}