{
    "video_id": "c9479bfb667e2b1ea29403289410f57c",
    "description": "",
    "url": "./data/segments/3N5aKGuJpFU-Scene-018.mp4",
    "frame_number": 0,
    "interval_seconds": 1,
    "batch_size": 2,
    "batch_step": 2,
    "caption": "The video appears to be a security camera footage capturing a nighttime scene. The environment is dimly lit, with a ladder leaning against a wall on the right side of the frame. There is a significant amount of smoke or fog filling the air, which obscures much of the view. Two white arrows are visible, pointing towards a small, indistinct object in the center of the frame. This object seems to be moving slightly, as indicated by its changing position between the two frames. The overall atmosphere suggests an event involving smoke or steam, possibly from a fire or some other source, and the presence of the arrows implies that the viewer's attention is being directed towards this particular area of interest."
}