{
    "video_id": "50e9351f4dad6580a98435172ba7acf9",
    "description": "",
    "url": "./data/segments/3P1vSUbet40-Scene-0810.mp4",
    "frame_number": 0,
    "interval_seconds": 1,
    "batch_size": 2,
    "batch_step": 2,
    "caption": "In the video, a person is seen holding a clear plastic case with both hands, carefully examining it. The case appears to be designed for storing and protecting collectible items, possibly trading cards or similar small objects. The individual's fingers gently grip the edges of the case, suggesting they are either opening it or ensuring its contents are secure. In the background, there are various boxes and shelves filled with similar items, indicating that this scene takes place in a store or a collection room dedicated to collectibles. A smaller inset in the bottom right corner shows another person, likely the host or commentator, who seems to be discussing the item being held. The setting and actions suggest that this video is part of a series where collectible items are showcased and reviewed."
}