{
    "video_id": "928e69eb6a9608c497542e8a37943bc4",
    "description": "",
    "url": "./data/segments/3q3CZaZLMiY-Scene-396.mp4",
    "frame_number": 0,
    "interval_seconds": 1,
    "batch_size": 2,
    "batch_step": 2,
    "caption": "The video features a man with a distinctive, spiky hairstyle and glasses, wearing a white shirt, yellow suspenders, and a red bow tie. He is seated in front of a microphone, suggesting he is participating in a podcast or radio show titled \"Boss Talk 101,\" as indicated by the logos on the screen. The man is wearing headphones and appears to be engaged in conversation, possibly discussing topics related to business or personal development. In the background, there is a woman with pink hair, dressed in a green outfit, who seems to be moving around, adding a dynamic element to the scene. The setting includes various posters and decorations, contributing to a casual yet professional atmosphere."
}