{
    "video_id": "e142b7e56faf482fae9bb43b5125b444",
    "description": "",
    "url": "./data/segments/3q3CZaZLMiY-Scene-628.mp4",
    "frame_number": 0,
    "interval_seconds": 1,
    "batch_size": 2,
    "batch_step": 2,
    "caption": "The video captures a formal meeting of the House Committee on General, Housing, and Military Affairs, dated April 12, 2019, focusing on S.23, a bill to increase the minimum wage. The scene is set in a conference room where several individuals, dressed in business attire, are seated around a long table equipped with microphones and documents. One man, wearing a suit and tie, is seen interacting with a laptop labeled \"NATIVE,\" possibly preparing or reviewing materials related to the discussion. As the camera pans across the room, it reveals other committee members engaged in various activities\u2014some are listening attentively, while others are handling papers or adjusting their positions. The atmosphere suggests a serious and professional setting, indicative of an important legislative session."
}