{
    "video_id": "322dc5c93adffe5267b55e4475c7b1a7",
    "description": "",
    "url": "./data/segments/3iUTkJy84EY-Scene-243.mp4",
    "frame_number": 0,
    "interval_seconds": 1,
    "batch_size": 2,
    "batch_step": 2,
    "caption": "The video captures a professional interview taking place at MongoDB World 2022, held at the Javits Center in New York, NY. Two men, both dressed in suits, are seated across from each other at a small round table equipped with a laptop and some papers. The interviewer, on the left, gestures animatedly as he speaks, while the interviewee listens attentively and responds. In the background, several people can be seen walking and conversing, indicating a bustling conference environment. The setting is well-lit, with modern architecture and signage visible, emphasizing the professional and tech-focused nature of the event. The video is sponsored by MongoDB, as indicated by the logo and text overlay."
}