{
  "video_id": "2ea9be89c7be84db4ac1340c647cdd57",
  "url": "./data/segments/3L_uHTClWfk-Scene-025.mp4",
  "n_frames": 4,
  "frame_timestamps": [
    0.221,
    0.663,
    1.104,
    1.546
  ],
  "grid_layout": "2x2",
  "model": "google/gemma-4-31B-it",
  "prompt_version": "v2-relabel",
  "caption": "A woman with blonde hair tied back in a ponytail is seen in profile against a plain, neutral-toned wall. She wears a black garment and a small stud earring in her ear. Throughout the sequence, she remains in the same position, facing right, and is captured from the chest up. Her expression is neutral, and her lips are slightly parted as if she is in the middle of speaking or about to speak. The lighting is soft and consistent, and there are no other people, objects, or text visible in the scene. There is very little movement between the frames, with only slight shifts in her facial expression and the positioning of her head as she looks forward."
}