{
    "video_id": "70eebe11c630d9abcc4e8f4d77c2495e",
    "description": "",
    "url": "./data/segments/3gZZFVx-9-M-Scene-035.mp4",
    "frame_number": 0,
    "interval_seconds": 1,
    "batch_size": 2,
    "batch_step": 2,
    "caption": "The video features two men engaged in a discussion, likely at a professional or academic event, as indicated by the poster in the background titled \"ALPHASZENSZOR\" which details typical gas sensor attributes. The man on the right, wearing a gray polo shirt and a name tag, appears to be explaining something with a focused expression, possibly addressing an audience or another participant. The man on the left, partially visible and wearing glasses and a checkered shirt, seems to be listening attentively. The setting suggests a formal presentation or workshop environment, with the poster providing context for the topic of discussion, which revolves around gas sensors and their applications."
}