{
    "video_id": "c46bc0cc76987b571cae8ff4ba5d00a7",
    "description": "",
    "url": "./data/segments/3kf1gQNnb-8-Scene-017.mp4",
    "frame_number": 0,
    "interval_seconds": 1,
    "batch_size": 2,
    "batch_step": 2,
    "caption": "The video appears to be a news broadcast from News18 India, covering a political event or rally. The central figure is seen sitting on top of a vehicle, waving to a crowd of supporters who are holding flags and banners. The scene suggests a lively and energetic atmosphere, typical of political gatherings. The text overlays indicate that the news segment is discussing a significant development related to the 2024 elections, with mentions of key political figures such as Tejashwi Yadav and Nitish Kumar. The breaking news banner at the bottom emphasizes the urgency and importance of the event being reported. The visuals and text together convey a sense of excitement and anticipation surrounding the political landscape in India."
}