{
    "video_id": "6d260028872c725de510d074d7190018",
    "description": "",
    "url": "./data/segments/3gJ0RZB6Df8-Scene-053.mp4",
    "frame_number": 0,
    "interval_seconds": 1,
    "batch_size": 2,
    "batch_step": 2,
    "caption": "The video showcases a person unboxing and examining collectible basketball trading cards, specifically featuring a card of Kevon Martin Jr. The main focus is on the detailed and vibrant design of the card, which is held up close to the camera for a clear view. In the background, there are additional boxes of trading cards stacked neatly, indicating a larger collection or ongoing unboxing session. The setting appears to be a professional environment, possibly a store or studio dedicated to trading card enthusiasts, as suggested by the logo \"JASPYS CASEBREAKS.COM\" displayed prominently. Another individual can be seen in the background, also engaged with the cards, adding to the communal and enthusiastic atmosphere of the scene. The overall tone of the video is one of excitement and appreciation for the collectible items being showcased."
}