{
    "video_id": "8a96b6a3824589562a34bd9e0228e1f8",
    "description": "",
    "url": "./data/segments/3q3CZaZLMiY-Scene-405.mp4",
    "frame_number": 0,
    "interval_seconds": 1,
    "batch_size": 2,
    "batch_step": 2,
    "caption": "The video features a person with a distinctive, spiky gray wig and glasses, wearing a white shirt, gold suspenders, and a red bow tie. They are seated in front of a microphone, suggesting they are participating in a podcast or radio show. The setting appears to be a studio or a room with a modern aesthetic, as indicated by the framed picture on the wall and the visible text \"UNIQUE FASHIONS\" in the background. The individual is wearing headphones and seems to be engaged in conversation, possibly discussing topics related to fashion or personal style, given the context and their attire. The logo \"BOSS TALK 101\" is prominently displayed, indicating the name of the podcast or show."
}