{
    "video_id": "67e7eb72c363f1ee8ba23a4814f8b0f9",
    "description": "",
    "url": "./data/segments/3P1vSUbet40-Scene-0535.mp4",
    "frame_number": 0,
    "interval_seconds": 1,
    "batch_size": 2,
    "batch_step": 2,
    "caption": "The video begins with an aerial view of a cityscape, showcasing a serene lake with a fountain in the foreground and a skyline of modern high-rise buildings in the background. The scene is calm, with the water reflecting the surrounding architecture and the partly cloudy sky above. As the video progresses, the camera pans to reveal a broader perspective of the urban area, transitioning to a waterfront promenade lined with palm trees and bordered by marinas filled with boats. The promenade is flanked by green spaces and pathways, leading towards a bustling city center with more high-rise buildings. The overall atmosphere is vibrant yet peaceful, highlighting the blend of natural beauty and urban development. The video concludes with the logo \"Tiger Real Estate LLC\" displayed on the screen, suggesting a promotional or real estate showcase."
}