{
    "video_id": "a3e349e4cfa00bb03f96242e003553af",
    "description": "",
    "url": "./data/segments/3iUTkJy84EY-Scene-127.mp4",
    "frame_number": 0,
    "interval_seconds": 1,
    "batch_size": 2,
    "batch_step": 2,
    "caption": "The video features a woman with shoulder-length dark hair and glasses, wearing a light green top with floral embroidery. She is seated against a plain black background, which helps to focus attention on her. The woman appears to be engaged in a conversation or delivering a speech, as she uses hand gestures to emphasize her points. Her expressions and movements suggest that she is explaining something with enthusiasm and clarity. A small microphone is clipped to her top, indicating that this might be a recorded lecture or presentation. The overall setting is simple and professional, likely intended for an educational or informative purpose."
}